pdf_crawler/__init__.py
pdf_crawler/data/downloaded_reports.json
pdf_crawler/fonts/FrutigerLTStd-Black.ttf
pdf_crawler/fonts/FrutigerLTStd-Bold.ttf
pdf_crawler/fonts/FrutigerLTStd-Cn.ttf
pdf_crawler/fonts/FrutigerLTStd-Italic.ttf
pdf_crawler/fonts/FrutigerLTStd-LightCn.ttf
pdf_crawler/fonts/FrutigerLTStd-Roman.ttf
pdf_crawler/report_generator.py
pdf_crawler/scripts.py
pdf_crawler/selenium_crawler.py
pdf_crawler/ui.py
pdf_crawler/Volume II Generator.bat
pdf_crawler-0.1.2.1.dist-info/entry_points.txt
pdf_crawler-0.1.2.1.dist-info/METADATA
pdf_crawler-0.1.2.1.dist-info/WHEEL
pdf_crawler-0.1.2.1.dist-info/RECORD
