Metadata-Version: 2.1
Name: pdf_crawler
Version: 0.1.2.1
Summary: Your project description
Author: Your Name
Author-email: your.email@example.com
Requires-Python: >=3.12,<4.0
Classifier: Programming Language :: Python :: 3
Classifier: Programming Language :: Python :: 3.12
Requires-Dist: PyMuPDF (>=1.22.3,<2.0.0)
Requires-Dist: beautifulsoup4 (>=4.12.3,<5.0.0)
Requires-Dist: natsort (>=8.4.0,<9.0.0)
Requires-Dist: pdfminer-six (>=20231228,<20231229)
Requires-Dist: pdfplumber (>=0.11.0,<0.12.0)
Requires-Dist: psutil (>=5.9.8,<6.0.0)
Requires-Dist: pypdf2 (>=3.0.1,<4.0.0)
Requires-Dist: pywin32 (>=306,<307)
Requires-Dist: reportlab (>=4.2.0,<5.0.0)
Requires-Dist: retry (>=0.9.2,<0.10.0)
Requires-Dist: selenium (>=4.22.0,<5.0.0)
Requires-Dist: setuptools (>=70.0.0,<71.0.0)
Requires-Dist: sv-ttk (>=2.6.0,<3.0.0)
Requires-Dist: webdriver-manager (>=4.0.1,<5.0.0)
